cowdao_cowpy/__init__.py
cowdao_cowpy/app_data/__init__.py
cowdao_cowpy/app_data/app_data_cid.py
cowdao_cowpy/app_data/app_data_doc.py
cowdao_cowpy/app_data/app_data_hex.py
cowdao_cowpy/app_data/consts.py
cowdao_cowpy/app_data/utils.py
cowdao_cowpy/codegen/__generated__/ComposableCow.py
cowdao_cowpy/codegen/__generated__/ExtensibleFallbackHandler.py
cowdao_cowpy/codegen/__generated__/Milkman.py
cowdao_cowpy/codegen/__generated__/TWAP.py
cowdao_cowpy/codegen/__init__.py
cowdao_cowpy/codegen/abi_handler.py
cowdao_cowpy/codegen/components/__init__.py
cowdao_cowpy/codegen/components/abi_loader.py
cowdao_cowpy/codegen/components/base_contract.py
cowdao_cowpy/codegen/components/base_mixin.py
cowdao_cowpy/codegen/components/contract_factory.py
cowdao_cowpy/codegen/components/contract_loader.py
cowdao_cowpy/codegen/components/get_abi_file.py
cowdao_cowpy/codegen/components/templates/__init__.py
cowdao_cowpy/codegen/components/templates/contract_template.hbs
cowdao_cowpy/codegen/components/templates/partials/__init__.py
cowdao_cowpy/codegen/components/templates/partials/contract_class.hbs
cowdao_cowpy/codegen/components/templates/partials/contract_mixin.hbs
cowdao_cowpy/codegen/components/templates/partials/dataclasses.hbs
cowdao_cowpy/codegen/components/templates/partials/enums.hbs
cowdao_cowpy/codegen/main.py
cowdao_cowpy/codegen/solidity_converter.py
cowdao_cowpy/common/api/api_base.py
cowdao_cowpy/common/api/decorators.py
cowdao_cowpy/common/api/errors.py
cowdao_cowpy/common/chains/__init__.py
cowdao_cowpy/common/chains/utils.py
cowdao_cowpy/common/config.py
cowdao_cowpy/common/constants.py
cowdao_cowpy/common/cow_error.py
cowdao_cowpy/composable/__init__.py
cowdao_cowpy/composable/conditional_order.py
cowdao_cowpy/composable/multiplexer.py
cowdao_cowpy/composable/order_types/__init__.py
cowdao_cowpy/composable/order_types/twap.py
cowdao_cowpy/composable/types.py
cowdao_cowpy/composable/utils.py
cowdao_cowpy/contracts/__init__.py
cowdao_cowpy-1.0.1.dist-info/LICENSE
cowdao_cowpy-1.0.1.dist-info/METADATA
cowdao_cowpy-1.0.1.dist-info/WHEEL
cowdao_cowpy-1.0.1.dist-info/RECORD
