Metadata-Version: 2.3
Name: cowdao-cowpy
Version: 1.0.1
Summary: 
Author: José Ribeiro
Author-email: jose@bleu.studio
Requires-Python: >=3.10,<4.0
Classifier: Programming Language :: Python :: 3
Classifier: Programming Language :: Python :: 3.10
Classifier: Programming Language :: Python :: 3.11
Classifier: Programming Language :: Python :: 3.12
Classifier: Programming Language :: Python :: 3.13
Requires-Dist: aiofiles (>=24.1.0,<25.0.0)
Requires-Dist: aiolimiter (>=1.1.0,<2.0.0)
Requires-Dist: backoff (>=2.2.1,<3.0.0)
Requires-Dist: eth-abi (>=5.1.0,<6.0.0)
Requires-Dist: eth-typing (>=4,<6)
Requires-Dist: httpx (>=0.23.0,<1.0.0)
Requires-Dist: jsonref (>=1.1.0,<2.0.0)
Requires-Dist: multiformats (>=0.3.1.post4,<0.4.0)
Requires-Dist: pycryptodomex (>=3.20.0,<4.0.0)
Requires-Dist: pydantic (>=2.7.0,<3.0.0)
Requires-Dist: pymerkle (>=5,<7)
Requires-Dist: pymultihash (>=0.8.2,<0.9.0)
Requires-Dist: web3 (>=6,<8)
